pyeo/__init__.py
pyeo/features/__init__.py
pyeo/features/code_free_ctor_visitor.py
pyeo/features/forbidden_decorator_visitor.py
pyeo/features/no_er_suffix.py
pyeo/features/no_getter_methods.py
pyeo/features/no_mutable_objects.py
pyeo/features/no_property_decorator.py
pyeo/features/no_public_attributes.py
pyeo/fk_plugin.py
pyeo/main.py
pyeo/py.typed
pyeo/utils/__init__.py
pyeo/utils/class_is_protocol.py
eo_styleguide-0.1.0.dist-info/METADATA
eo_styleguide-0.1.0.dist-info/WHEEL
eo_styleguide-0.1.0.dist-info/entry_points.txt
eo_styleguide-0.1.0.dist-info/RECORD
