Metadata-Version: 2.4
Name: eo-styleguide
Version: 0.1.0
Summary: Pyeo is an advanced static analysis tool tailored specifically to enforce the principles advocated by Elegant Objects (elegantobjects.org) in Python projects. It serves as a quality control instrument to ensure that your Python code adheres to the core tenets of elegance, simplicity, and maintainability.
License: MIT
Author: Almaz Ilaletdinov
Author-email: a.ilaletdinov@yandex.ru
Requires-Python: >=3.9,<4.0
Classifier: License :: OSI Approved :: MIT License
Classifier: Programming Language :: Python :: 3
Classifier: Programming Language :: Python :: 3.9
Classifier: Programming Language :: Python :: 3.10
Classifier: Programming Language :: Python :: 3.11
Classifier: Programming Language :: Python :: 3.12
Classifier: Programming Language :: Python :: 3.13
Classifier: Programming Language :: Python :: 3.14
Requires-Dist: flake8 (>=7.1,<8.0)
Requires-Dist: flake8-final
Requires-Dist: flake8-override
